magic_doc/__init__.py
magic_doc/cli.py
magic_doc/docconv.py
magic_doc/pdf_transform.py
magic_doc/bin/linux/antiword
magic_doc/bin/linux/share/antiword/8859-1.txt
magic_doc/bin/linux/share/antiword/8859-10.txt
magic_doc/bin/linux/share/antiword/8859-11.txt
magic_doc/bin/linux/share/antiword/8859-13.txt
magic_doc/bin/linux/share/antiword/8859-14.txt
magic_doc/bin/linux/share/antiword/8859-15.txt
magic_doc/bin/linux/share/antiword/8859-16.txt
magic_doc/bin/linux/share/antiword/8859-2.txt
magic_doc/bin/linux/share/antiword/8859-3.txt
magic_doc/bin/linux/share/antiword/8859-4.txt
magic_doc/bin/linux/share/antiword/8859-5.txt
magic_doc/bin/linux/share/antiword/8859-6.txt
magic_doc/bin/linux/share/antiword/8859-7.txt
magic_doc/bin/linux/share/antiword/8859-8.txt
magic_doc/bin/linux/share/antiword/8859-9.txt
magic_doc/bin/linux/share/antiword/Default
magic_doc/bin/linux/share/antiword/Example
magic_doc/bin/linux/share/antiword/MacCyrillic.txt
magic_doc/bin/linux/share/antiword/MacRoman.txt
magic_doc/bin/linux/share/antiword/UTF-8.txt
magic_doc/bin/linux/share/antiword/Unicode01
magic_doc/bin/linux/share/antiword/Unicode15
magic_doc/bin/linux/share/antiword/cp1250.txt
magic_doc/bin/linux/share/antiword/cp1251.txt
magic_doc/bin/linux/share/antiword/cp1252.txt
magic_doc/bin/linux/share/antiword/cp437.txt
magic_doc/bin/linux/share/antiword/cp850.txt
magic_doc/bin/linux/share/antiword/cp852.txt
magic_doc/bin/linux/share/antiword/cp862.txt
magic_doc/bin/linux/share/antiword/cp864.txt
magic_doc/bin/linux/share/antiword/cp866.txt
magic_doc/bin/linux/share/antiword/fontnames
magic_doc/bin/linux/share/antiword/fontnames.russian
magic_doc/bin/linux/share/antiword/koi8-r.txt
magic_doc/bin/linux/share/antiword/koi8-u.txt
magic_doc/bin/linux/share/antiword/roman.txt
magic_doc/common/__init__.py
magic_doc/common/default_config.py
magic_doc/contrib/__init__.py
magic_doc/contrib/wrapper_exceptions.py
magic_doc/contrib/model/__init__.py
magic_doc/contrib/office/__init__.py
fairy_doc-0.1.44.dist-info/LICENSE
fairy_doc-0.1.44.dist-info/METADATA
fairy_doc-0.1.44.dist-info/WHEEL
fairy_doc-0.1.44.dist-info/entry_points.txt
fairy_doc-0.1.44.dist-info/top_level.txt
fairy_doc-0.1.44.dist-info/RECORD
