Metadata-Version: 2.1
Name: fairy-doc
Version: 0.1.44
Summary: A lightweight toolbox to manipulate documents
Home-page: https://github.com/InternLM/magic-doc
License: Apache 2.0
Requires-Python: >=3.10, <3.11
License-File: LICENSE
Requires-Dist: alembic ==1.13.1
Requires-Dist: aniso8601 ==9.0.1
Requires-Dist: blinker ==1.8.2
Requires-Dist: cchardet ==2.1.7
Requires-Dist: certifi ==2024.2.2
Requires-Dist: charset-normalizer ==3.3.2
Requires-Dist: docopt ==0.6.2
Requires-Dist: Flask ==3.0.3
Requires-Dist: Flask-Cors ==4.0.1
Requires-Dist: Flask-JWT-Extended ==4.6.0
Requires-Dist: flask-marshmallow ==1.2.1
Requires-Dist: Flask-Migrate ==4.0.7
Requires-Dist: Flask-RESTful ==0.3.10
Requires-Dist: Flask-SQLAlchemy ==3.1.1
Requires-Dist: func-timeout ==4.3.5
Requires-Dist: greenlet ==3.0.3
Requires-Dist: idna ==3.7
Requires-Dist: itsdangerous ==2.2.0
Requires-Dist: Jinja2 ==3.1.4
Requires-Dist: lark-parser ==0.12.0
Requires-Dist: lxml ==5.1.1
Requires-Dist: Mako ==1.3.5
Requires-Dist: MarkupSafe ==2.1.5
Requires-Dist: marshmallow ==3.21.2
Requires-Dist: marshmallow-sqlalchemy ==1.0.0
Requires-Dist: packaging ==24.0
Requires-Dist: py-asciimath ==0.3.0
Requires-Dist: PyJWT ==2.8.0
Requires-Dist: pytz ==2024.1
Requires-Dist: PyYAML ==6.0.1
Requires-Dist: requests ==2.32.2
Requires-Dist: six ==1.16.0
Requires-Dist: SQLAlchemy ==2.0.30
Requires-Dist: typing-extensions ==4.11.0
Requires-Dist: urllib3
Requires-Dist: Werkzeug ==3.0.3
Requires-Dist: python-pptx
Requires-Dist: s3pathlib
Requires-Dist: PyMuPDF ==1.24.5
Requires-Dist: smart-open[s3]
Provides-Extra: cpu
Requires-Dist: paddlepaddle ==2.5.2 ; extra == 'cpu'
Requires-Dist: paddleocr ==2.7.3 ; extra == 'cpu'
Requires-Dist: magic-pdf[cpu] ==0.5.11 ; extra == 'cpu'
Provides-Extra: gpu
Requires-Dist: paddlepaddle-gpu ==2.6.1 ; extra == 'gpu'
Requires-Dist: paddleocr ==2.7.3 ; extra == 'gpu'
Requires-Dist: magic-pdf[gpu] ==0.5.11 ; extra == 'gpu'
